Metadata-Version: 2.1
Name: urlopenlib
Version: 1.0.1
Summary: 你可以用它来爬虫
Home-page: https://github.com/
Author: Jianrui Li
Author-email: lijianrui7560@qq.com
License: UNKNOWN
Platform: UNKNOWN
Classifier: Programming Language :: Python :: 3
Classifier: License :: OSI Approved :: MIT License
Classifier: Operating System :: OS Independent
